{
    "sourceFile": "src/Components/NavBar.jsx",
    "activeCommit": 0,
    "commits": [
        {
            "activePatchIndex": 2,
            "patches": [
                {
                    "date": 1757675606947,
                    "content": "Index: \n===================================================================\n--- \n+++ \n"
                },
                {
                    "date": 1757675616936,
                    "content": "Index: \n===================================================================\n--- \n+++ \n@@ -2,15 +2,13 @@\n     return (\r\n         <nav>\r\n             <div className=\"navTitle\">\r\n                 <strong>\r\n-                    <ul class=\"dropdown-menu dropdown-menu-dark\">\r\n+                    <ul class=\"dropdown-menu dropdown-menu-dark\" name=\"categery\">\r\n                         <li><a class=\"dropdown-item\" href=\"#\">Movies</a></li>\r\n                         <li><a class=\"dropdown-item\" href=\"#\">TV Shows</a></li>\r\n                     </ul>\r\n-                    <select name=\"categery\" id=\"\">\r\n-                        <option value=\"Movies\">Movies</option>\r\n-                        <option value=\"TV Shows\"></option>\r\n+                    <select  id=\"\">\r\n                     </select>\r\n                 </strong>\r\n             </div>\r\n             <div>\r\n"
                },
                {
                    "date": 1757675631307,
                    "content": "Index: \n===================================================================\n--- \n+++ \n@@ -2,9 +2,9 @@\n     return (\r\n         <nav>\r\n             <div className=\"navTitle\">\r\n                 <strong>\r\n-                    <ul class=\"dropdown-menu dropdown-menu-dark\" name=\"categery\">\r\n+                    <ul class=\"dropdown-menu dropdown-menu-dark\" >\r\n                         <li><a class=\"dropdown-item\" href=\"#\">Movies</a></li>\r\n                         <li><a class=\"dropdown-item\" href=\"#\">TV Shows</a></li>\r\n                     </ul>\r\n                     <select id=\"\">\r\n"
                }
            ],
            "date": 1757675606947,
            "name": "Commit-0",
            "content": "function NavBar() {\r\n    return (\r\n        <nav>\r\n            <div className=\"navTitle\">\r\n                <strong>\r\n                    <ul class=\"dropdown-menu dropdown-menu-dark\">\r\n                        <li><a class=\"dropdown-item\" href=\"#\">Movies</a></li>\r\n                        <li><a class=\"dropdown-item\" href=\"#\">TV Shows</a></li>\r\n                    </ul>\r\n                    <select name=\"categery\" id=\"\">\r\n                    <option value=\"Movies\">Movies</option>\r\n                    <option value=\"TV Shows\"></option>\r\n                </select>\r\n                </strong>\r\n            </div>\r\n            <div>\r\n                <select name=\"lang\" id=\"\">\r\n                    <option value=\"En\">En</option>\r\n                    <option value=\"Ar\">Ar</option>\r\n                </select>\r\n                <span>\r\n                    <a href=\"#\">\r\n                       <img src=\"\" alt=\"\" />\r\n                        Watch List\r\n                    </a>\r\n                </span>\r\n            </div>\r\n        </nav>\r\n\r\n    )\r\n}\r\nexport default NavBar"
        }
    ]
}